Mux.v
module Mux(opt1, opt2, out, select);
input [31:0] opt1, opt2;
input select;

output reg [31:0] out;

always@(opt1 or opt2 or select) begin
	out = select ? opt2 : opt1;
	$display("opt1: %b, opt2: %b", opt1, opt2);
end
endmodule

MuxTest.v
`include "Mux.v"

module MuxTest();
    reg [31:0] in1, in2;
    reg select;
    wire [31:0] out;
    reg [3:0] test_vals;

    Mux mux (in1, in2, out, select);

    initial begin
	$dumpfile("MuxTest.vcd");
	$dumpvars(0, MuxTest);
	$display("MuxTest Test");
	test_vals = 0;
	in1 = 32'b0;
	in2 = 32'b0;

	for(test_vals = 0;test_vals < 8;test_vals = test_vals + 1) begin
		{in1[0],in2[1],select} = test_vals[2:0];
		#5
		$display("in0 = %d, in1 = %d, select = %b. Output = %d",
 		in1, in2, select, out);
	end

    end
endmodule

MuxTest.vcd
$date
	Sat Nov 24 18:10:46 2018
$end
$version
	Icarus Verilog
$end
$timescale
	1s
$end
$scope module MuxTest $end
$var wire 32 ! out [31:0] $end
$var reg 32 " in1 [31:0] $end
$var reg 32 # in2 [31:0] $end
$var reg 1 $ select $end
$var reg 4 % test_vals [3:0] $end
$scope module mux $end
$var wire 32 & opt1 [31:0] $end
$var wire 32 ' opt2 [31:0] $end
$var wire 1 $ select $end
$var reg 32 ( out [31:0] $end
$upscope $end
$upscope $end
$enddefinitions $end
#0
$dumpvars
b0 (
b0 '
b0 &
b0 %
0$
b0 #
b0 "
b0 !
$end
#5
1$
b1 %
#10
b10 !
b10 (
b10 #
b10 '
0$
b10 %
#15
b0 !
b0 (
1$
b11 %
#20
b1 "
b1 &
b0 #
b0 '
0$
b100 %
#25
b1 !
b1 (
1$
b101 %
#30
b10 !
b10 (
b10 #
b10 '
0$
b110 %
#35
b1 !
b1 (
1$
b111 %
#40
b1000 %
